{
    "name": "Quickdraw",
    "variant": "QKD-5A",
    "maxTons": 60,
    "currentTons": 60,
    "defaultAlphaStrike": 182,
    "defaultAlphaStrikeStab": 12,
    "defaultAlphaHeatTotal": 80,
    "defaultHeatDisp": 45,
    "currentTotalArmor": 640,
    "maxTotalArmor": 1245,
    "armor": {
        "head": 45,
        "headMax": 45,
        "centerTorso": 85,
        "centerTorsoMax": 200,
        "centerTorsoRear": 40,
        "centerTorsoRearMax": 100,
        "rightTorso": 70,
        "rightTorsoMax": 140,
        "rightTorsoRear": 35,
        "rightTorsoRearMax": 70,
        "leftTorso": 70,
        "leftTorsoMax": 140,
        "leftTorsoRear": 35,
        "leftTorsoRearMax": 70,
        "rightArm": 55,
        "rightArmMax": 100,
        "leftArm": 55,
        "leftArmMax": 100,
        "rightLeg": 75,
        "rightLegMax": 140,
        "leftLeg": 75,
        "leftLegMax": 140
    },
    "hardPoints": {
        "head": {
            "energy": 0,
            "ballistic": 0,
            "missile": 0,
            "support": 0
        },
        "centerTorso": {
            "energy": 0,
            "ballistic": 0,
            "missile": 0,
            "support": 2
        },
        "rightTorso": {
            "energy": 2,
            "ballistic": 0,
            "missile": 0,
            "support": 0
        },
        "leftTorso": {
            "energy": 2,
            "ballistic": 0,
            "missile": 1,
            "support": 0
        },
        "rightArm": {
            "energy": 1,
            "ballistic": 0,
            "missile": 0,
            "support": 0
        },
        "leftArm": {
            "energy": 1,
            "ballistic": 0,
            "missile": 0,
            "support": 0
        },
        "rightLeg": {
            "energy": 0,
            "ballistic": 0,
            "missile": 0,
            "support": 0
        },
        "leftLeg": {
            "energy": 0,
            "ballistic": 0,
            "missile": 0,
            "support": 0
        }
    },
    "defaultHeatsinks": {
        "head": 0,
        "centerTorso": 1,
        "rightTorso": 0,
        "leftTorso": 0,
        "rightArm": 0,
        "leftArm": 0,
        "rightLeg": 2,
        "leftLeg": 2
    },
    "defaultJumpJets": {
        "head": 0,
        "centerTorso": 1,
        "rightTorso": 1,
        "leftTorso": 1,
        "rightArm": 0,
        "leftArm": 0,
        "rightLeg": 2,
        "leftLeg": 2
    },
    "defaultEquipment": {
        
    },
    "defaultWeapons": {
        "centerTorso": [
            {
                "ammo": "false",
                "category": "missile",
                "name": "srm4-0",
                "origin": "default",
                "slots": 1,
                "title": "SRM-4",
                "weight": 2,
                "shots": 4,
                "damage": 8,
                "stabdamage": 3,
                "heat": 8
            }
        ],
        "rightTorso": [
            {
                "ammo": "false",
                "category": "energy",
                "name": "mediumLaser0",
                "origin": "default",
                "slots": 1,
                "title": "Medium Laser",
                "weight": 1,
                "shots": 1,
                "damage": 25,
                "stabdamage": 0,
                "heat": 12
            },
            {
                "ammo": "false",
                "category": "energy",
                "name": "mediumLaser0",
                "origin": "default",
                "slots": 1,
                "title": "Medium Laser",
                "weight": 1,
                "shots": 1,
                "damage": 25,
                "stabdamage": 0,
                "heat": 12
            },
            {
                "ammo": "true",
                "category": "missile",
                "name": "srmAmmo",
                "origin": "default",
                "slots": 1,
                "title": "SRM Ammo",
                "weight": 1
            },
            {
                "ammo": "true",
                "category": "missile",
                "name": "srmAmmo",
                "origin": "default",
                "slots": 1,
                "title": "SRM Ammo",
                "weight": 1
            }
        ],
        "leftTorso": [
            {
                "ammo": "false",
                "category": "energy",
                "name": "mediumLaser0",
                "origin": "default",
                "slots": 1,
                "title": "Medium Laser",
                "weight": 1,
                "shots": 1,
                "damage": 25,
                "stabdamage": 0,
                "heat": 12
            },
            {
                "ammo": "false",
                "category": "energy",
                "name": "mediumLaser0",
                "origin": "default",
                "slots": 1,
                "title": "Medium Laser",
                "weight": 1,
                "shots": 1,
                "damage": 25,
                "stabdamage": 0,
                "heat": 12
            }
        ],
        "leftArm": [
            {
                "ammo": "false",
                "category": "energy",
                "name": "mediumLaser0",
                "origin": "default",
                "slots": 1,
                "title": "Medium Laser",
                "weight": 1,
                "shots": 1,
                "damage": 25,
                "stabdamage": 0,
                "heat": 12
            }   
        ],
        "rightArm": [
            {
                "ammo": "false",
                "category": "energy",
                "name": "mediumLaser0",
                "origin": "default",
                "slots": 1,
                "title": "Medium Laser",
                "weight": 1,
                "shots": 1,
                "damage": 25,
                "stabdamage": 0,
                "heat": 12
            }  
        ]
    }
}